deeprtalign/__init__.py
deeprtalign/__main__.py
deeprtalign/collect_mass_alignment.py
deeprtalign/collect_mass_alignment_no_disk.py
deeprtalign/collect_mass_information_shift_bins_no_disk.py
deeprtalign/collect_time_shift.py
deeprtalign/collect_time_shift_no_disk.py
deeprtalign/main.py
deeprtalign/mass_alignment_samples.py
deeprtalign/mass_alignment_samples_multi.py
deeprtalign/mass_alignment_samples_multi_no_disk.py
deeprtalign/mass_alignment_samples_no_disk.py
deeprtalign/mass_information_filter.py
deeprtalign/mass_information_filter_multi.py
deeprtalign/mass_information_filter_multi_no_disk.py
deeprtalign/mass_information_filter_no_disk.py
deeprtalign/collect_mass_information_shift_bins/__init__.py
deeprtalign/collect_mass_information_shift_bins/dinosaur.py
deeprtalign/collect_mass_information_shift_bins/maxquant.py
deeprtalign/collect_mass_information_shift_bins/openms.py
deeprtalign/collect_mass_information_shift_bins/xicfinder.py
deeprtalign/data/base.npy
deeprtalign/data/params.pt
deeprtalign/pre_step/__init__.py
deeprtalign/pre_step/dinosaur.py
deeprtalign/pre_step/maxquant.py
deeprtalign/pre_step/openms.py
deeprtalign/pre_step/other_csv.py
deeprtalign/pre_step/other_txt.py
deeprtalign/pre_step/xicfinder.py
deeprtalign/pre_step_no_disk/__init__.py
deeprtalign/pre_step_no_disk/dinosaur_no_disk.py
deeprtalign/pre_step_no_disk/maxquant_no_disk.py
deeprtalign/pre_step_no_disk/openms_no_disk.py
deeprtalign/pre_step_no_disk/other_csv_no_disk.py
deeprtalign/pre_step_no_disk/other_txt_no_disk.py
deeprtalign/pre_step_no_disk/xicfinder_no_disk.py
deeprtalign-1.2.2.dist-info/METADATA
deeprtalign-1.2.2.dist-info/WHEEL
deeprtalign-1.2.2.dist-info/entry_points.txt
deeprtalign-1.2.2.dist-info/top_level.txt
deeprtalign-1.2.2.dist-info/RECORD
