Metadata-Version: 2.1
Name: deeprtalign
Version: 1.2.2
Summary: retention time alignment tool for large cohort LC-MS data analysis
Home-page: https://github.com/FineLiu/deeprtalign
Author: Yi Liu
Author-email: leoicarus@163.com
License: GPLv3
Platform: UNKNOWN
Requires-Python: >=3.4
Requires-Dist: xlrd (==1.2.0)
Requires-Dist: pandas (>=0.24)
